flexy_token/__init__.py
flexy_token/api_client.py
flexy_token/get_url.py
flexy_token-0.11.dist-info/LICENSE
flexy_token-0.11.dist-info/METADATA
flexy_token-0.11.dist-info/WHEEL
flexy_token-0.11.dist-info/top_level.txt
flexy_token-0.11.dist-info/RECORD
