Metadata-Version: 2.1
Name: flexy_token
Version: 0.11
Summary: Package for the Token
Home-page: https://github.com/saikrishna7660/flexy_token
Author: Saikrishna Macha
Author-email: saikrishna.macha@flexydial.in
License: MIT
License-File: LICENSE
Requires-Dist: requests
